LICENSE.txt
MANIFEST.in
README.rst
setup.py
djangoshop_subscribe.egg-info/PKG-INFO
djangoshop_subscribe.egg-info/SOURCES.txt
djangoshop_subscribe.egg-info/dependency_links.txt
djangoshop_subscribe.egg-info/not-zip-safe
djangoshop_subscribe.egg-info/requires.txt
djangoshop_subscribe.egg-info/top_level.txt
shop_subscribe/__init__.py
shop_subscribe/admin.py
shop_subscribe/apps.py
shop_subscribe/cmsplugin_cascade.py
shop_subscribe/forms.py
shop_subscribe/models.py
shop_subscribe/serializers.py
shop_subscribe/urls.py
shop_subscribe/utils.py
shop_subscribe/views.py
shop_subscribe/static/.DS_Store
shop_subscribe/static/shop_subscribe/css/djng-success.scss
shop_subscribe/templates/.DS_Store
shop_subscribe/templates/Email-Framework-master/.DS_Store
shop_subscribe/templates/Email-Framework-master/README.md
shop_subscribe/templates/Email-Framework-master/boilerplate.html
shop_subscribe/templates/Email-Framework-master/mail.css
shop_subscribe/templates/Email-Framework-master/grids/grid-200-400.html
shop_subscribe/templates/Email-Framework-master/grids/grid-400-200.html
shop_subscribe/templates/Email-Framework-master/grids/grid-master.html
shop_subscribe/templates/Email-Framework-master/grids/grid1.html
shop_subscribe/templates/Email-Framework-master/grids/grid2.html
shop_subscribe/templates/Email-Framework-master/grids/grid3.html
shop_subscribe/templates/Email-Framework-master/grids/grid4.html
shop_subscribe/templates/Email-Framework-master/grids/grid5.html
shop_subscribe/templates/Email-Framework-master/images/spacer.gif
shop_subscribe/templates/Email-Framework-master/modules/module-master.html
shop_subscribe/templates/Email-Framework-master/modules/buttons/border-radius-button.html
shop_subscribe/templates/Email-Framework-master/modules/buttons/center-aligned-button.html
shop_subscribe/templates/Email-Framework-master/modules/buttons/center-side-by-side-buttons.html
shop_subscribe/templates/Email-Framework-master/modules/buttons/ghost-button.html
shop_subscribe/templates/Email-Framework-master/modules/buttons/left-aligned-button.html
shop_subscribe/templates/Email-Framework-master/modules/buttons/right-aligned-button.html
shop_subscribe/templates/Email-Framework-master/modules/content-panels/1-block-image-content.html
