Metadata-Version: 1.1
Name: djangoshop-subscribe
Version: 0.2.0
Summary: An email subscription plugin for Django-SHOP
Home-page: https://github.com/racitup/djangoshop-subscribe
Author: Richard Case
Author-email: rich@racitup.com
License: BSD License
Keywords: Django,Django-SHOP
Platform: OS Independent
Classifier: Environment :: Web Environment
Classifier: Framework :: Django
Classifier: Intended Audience :: Developers
Classifier: License :: OSI Approved :: BSD License
Classifier: Operating System :: OS Independent
Classifier: Programming Language :: Python :: 2.7
Classifier: Programming Language :: Python :: 3.5
Classifier: Topic :: Software Development :: Libraries :: Application Frameworks
Classifier: Topic :: Internet :: WWW/HTTP :: Dynamic Content
